[
 {
  "allow_in_quick_entry": 0,
  "allow_on_submit": 0,
  "bold": 0,
  "collapsible": 0,
  "collapsible_depends_on": null,
  "columns": 0,
  "default": null,
  "depends_on": null,
  "description": null,
  "docstatus": 0,
  "doctype": "Custom Field",
  "dt": "Payment Entry Detail",
  "fetch_from": null,
  "fetch_if_empty": 0,
  "fieldname": "sup_and_exp",
  "fieldtype": "Select",
  "hidden": 0,
  "hide_border": 0,
  "hide_days": 0,
  "hide_seconds": 0,
  "ignore_user_permissions": 0,
  "ignore_xss_filter": 0,
  "in_global_search": 0,
  "in_list_view": 1,
  "in_preview": 0,
  "in_standard_filter": 0,
  "insert_after": null,
  "is_system_generated": 0,
  "is_virtual": 0,
  "label": "sup_and_exp",
  "length": 0,
  "mandatory_depends_on": null,
  "modified": "2023-03-08 14:01:29.494888",
  "module": null,
  "name": "Payment Entry Detail-sup_and_exp",
  "no_copy": 0,
  "non_negative": 0,
  "options": "\nSupplier\nExpense",
  "permlevel": 0,
  "precision": "",
  "print_hide": 0,
  "print_hide_if_no_value": 0,
  "print_width": null,
  "read_only": 0,
  "read_only_depends_on": null,
  "report_hide": 0,
  "reqd": 0,
  "search_index": 0,
  "translatable": 1,
  "unique": 0,
  "width": null
 },
 {
  "allow_in_quick_entry": 0,
  "allow_on_submit": 0,
  "bold": 0,
  "collapsible": 0,
  "collapsible_depends_on": null,
  "columns": 0,
  "default": null,
  "depends_on": null,
  "description": null,
  "docstatus": 0,
  "doctype": "Custom Field",
  "dt": "Payment Allocation",
  "fetch_from": null,
  "fetch_if_empty": 0,
  "fieldname": "invoice_ammount",
  "fieldtype": "Float",
  "hidden": 0,
  "hide_border": 0,
  "hide_days": 0,
  "hide_seconds": 0,
  "ignore_user_permissions": 0,
  "ignore_xss_filter": 0,
  "in_global_search": 0,
  "in_list_view": 1,
  "in_preview": 0,
  "in_standard_filter": 0,
  "insert_after": "paid_amount",
  "is_system_generated": 0,
  "is_virtual": 0,
  "label": "Invoice Ammount",
  "length": 0,
  "mandatory_depends_on": null,
  "modified": "2023-03-29 12:43:51.428934",
  "module": null,
  "name": "Payment Allocation-invoice_ammount",
  "no_copy": 0,
  "non_negative": 0,
  "options": null,
  "permlevel": 0,
  "precision": "",
  "print_hide": 0,
  "print_hide_if_no_value": 0,
  "print_width": null,
  "read_only": 0,
  "read_only_depends_on": null,
  "report_hide": 0,
  "reqd": 0,
  "search_index": 0,
  "translatable": 0,
  "unique": 0,
  "width": null
 },
 {
  "allow_in_quick_entry": 0,
  "allow_on_submit": 0,
  "bold": 0,
  "collapsible": 0,
  "collapsible_depends_on": null,
  "columns": 0,
  "default": null,
  "depends_on": "",
  "description": null,
  "docstatus": 0,
  "doctype": "Custom Field",
  "dt": "Payment Entry Detail",
  "fetch_from": null,
  "fetch_if_empty": 0,
  "fieldname": "supplier",
  "fieldtype": "Link",
  "hidden": 0,
  "hide_border": 0,
  "hide_days": 0,
  "hide_seconds": 0,
  "ignore_user_permissions": 0,
  "ignore_xss_filter": 0,
  "in_global_search": 0,
  "in_list_view": 1,
  "in_preview": 0,
  "in_standard_filter": 0,
  "insert_after": "sup_and_exp",
  "is_system_generated": 0,
  "is_virtual": 0,
  "label": "Supplier",
  "length": 0,
  "mandatory_depends_on": null,
  "modified": "2023-03-08 15:20:15.045787",
  "module": null,
  "name": "Payment Entry Detail-supplier",
  "no_copy": 0,
  "non_negative": 0,
  "options": "Supplier",
  "permlevel": 0,
  "precision": "",
  "print_hide": 0,
  "print_hide_if_no_value": 0,
  "print_width": null,
  "read_only": 0,
  "read_only_depends_on": null,
  "report_hide": 0,
  "reqd": 0,
  "search_index": 0,
  "translatable": 0,
  "unique": 0,
  "width": null
 },
 {
  "allow_in_quick_entry": 0,
  "allow_on_submit": 0,
  "bold": 0,
  "collapsible": 0,
  "collapsible_depends_on": null,
  "columns": 0,
  "default": null,
  "depends_on": null,
  "description": null,
  "docstatus": 0,
  "doctype": "Custom Field",
  "dt": "Payment Allocation",
  "fetch_from": "purchase.balance_ammount",
  "fetch_if_empty": 1,
  "fieldname": "balance_ammount",
  "fieldtype": "Float",
  "hidden": 0,
  "hide_border": 0,
  "hide_days": 0,
  "hide_seconds": 0,
  "ignore_user_permissions": 0,
  "ignore_xss_filter": 0,
  "in_global_search": 0,
  "in_list_view": 1,
  "in_preview": 0,
  "in_standard_filter": 0,
  "insert_after": "invoice_ammount",
  "is_system_generated": 0,
  "is_virtual": 0,
  "label": "Balance Amount",
  "length": 0,
  "mandatory_depends_on": null,
  "modified": "2023-03-29 12:43:51.631746",
  "module": null,
  "name": "Payment Allocation-balance_ammount",
  "no_copy": 0,
  "non_negative": 0,
  "options": null,
  "permlevel": 0,
  "precision": "",
  "print_hide": 0,
  "print_hide_if_no_value": 0,
  "print_width": null,
  "read_only": 0,
  "read_only_depends_on": null,
  "report_hide": 0,
  "reqd": 0,
  "search_index": 0,
  "translatable": 0,
  "unique": 0,
  "width": null
 },
 {
  "allow_in_quick_entry": 0,
  "allow_on_submit": 1,
  "bold": 0,
  "collapsible": 0,
  "collapsible_depends_on": null,
  "columns": 0,
  "default": null,
  "depends_on": null,
  "description": null,
  "docstatus": 0,
  "doctype": "Custom Field",
  "dt": "Payment Allocation",
  "fetch_from": null,
  "fetch_if_empty": 0,
  "fieldname": "pay",
  "fieldtype": "Float",
  "hidden": 0,
  "hide_border": 0,
  "hide_days": 0,
  "hide_seconds": 0,
  "ignore_user_permissions": 0,
  "ignore_xss_filter": 0,
  "in_global_search": 0,
  "in_list_view": 1,
  "in_preview": 0,
  "in_standard_filter": 0,
  "insert_after": "purchase",
  "is_system_generated": 0,
  "is_virtual": 0,
  "label": "Pay",
  "length": 0,
  "mandatory_depends_on": null,
  "modified": "2023-03-30 12:15:06.862379",
  "module": null,
  "name": "Payment Allocation-pay",
  "no_copy": 0,
  "non_negative": 0,
  "options": null,
  "permlevel": 0,
  "precision": "",
  "print_hide": 0,
  "print_hide_if_no_value": 0,
  "print_width": null,
  "read_only": 0,
  "read_only_depends_on": null,
  "report_hide": 0,
  "reqd": 0,
  "search_index": 0,
  "translatable": 0,
  "unique": 0,
  "width": null
 },
 {
  "allow_in_quick_entry": 0,
  "allow_on_submit": 1,
  "bold": 0,
  "collapsible": 0,
  "collapsible_depends_on": null,
  "columns": 0,
  "default": null,
  "depends_on": null,
  "description": null,
  "docstatus": 0,
  "doctype": "Custom Field",
  "dt": "Payment Entry Detail",
  "fetch_from": null,
  "fetch_if_empty": 0,
  "fieldname": "total_amount",
  "fieldtype": "Float",
  "hidden": 0,
  "hide_border": 0,
  "hide_days": 0,
  "hide_seconds": 0,
  "ignore_user_permissions": 0,
  "ignore_xss_filter": 0,
  "in_global_search": 0,
  "in_list_view": 1,
  "in_preview": 0,
  "in_standard_filter": 0,
  "insert_after": "amount",
  "is_system_generated": 0,
  "is_virtual": 0,
  "label": "Total Amount",
  "length": 0,
  "mandatory_depends_on": null,
  "modified": "2023-04-02 10:46:56.614547",
  "module": null,
  "name": "Payment Entry Detail-total_amount",
  "no_copy": 0,
  "non_negative": 0,
  "options": null,
  "permlevel": 0,
  "precision": "",
  "print_hide": 0,
  "print_hide_if_no_value": 0,
  "print_width": null,
  "read_only": 1,
  "read_only_depends_on": null,
  "report_hide": 0,
  "reqd": 0,
  "search_index": 0,
  "translatable": 0,
  "unique": 0,
  "width": null
 },
 {
  "allow_in_quick_entry": 0,
  "allow_on_submit": 0,
  "bold": 0,
  "collapsible": 0,
  "collapsible_depends_on": null,
  "columns": 0,
  "default": null,
  "depends_on": null,
  "description": null,
  "docstatus": 0,
  "doctype": "Custom Field",
  "dt": "Payment Entry Detail",
  "fetch_from": null,
  "fetch_if_empty": 0,
  "fieldname": "payment_entry_details",
  "fieldtype": "Link",
  "hidden": 1,
  "hide_border": 0,
  "hide_days": 0,
  "hide_seconds": 0,
  "ignore_user_permissions": 0,
  "ignore_xss_filter": 0,
  "in_global_search": 0,
  "in_list_view": 1,
  "in_preview": 0,
  "in_standard_filter": 0,
  "insert_after": "clearance_date",
  "is_system_generated": 0,
  "is_virtual": 0,
  "label": "Payment Allocation",
  "length": 0,
  "mandatory_depends_on": null,
  "modified": "2023-03-29 15:32:02.059494",
  "module": null,
  "name": "Payment Entry Detail-payment_entry_details",
  "no_copy": 0,
  "non_negative": 0,
  "options": "Payment entry Details",
  "permlevel": 0,
  "precision": "",
  "print_hide": 0,
  "print_hide_if_no_value": 0,
  "print_width": null,
  "read_only": 0,
  "read_only_depends_on": null,
  "report_hide": 0,
  "reqd": 0,
  "search_index": 0,
  "translatable": 0,
  "unique": 0,
  "width": null
 },
 {
  "allow_in_quick_entry": 0,
  "allow_on_submit": 1,
  "bold": 0,
  "collapsible": 0,
  "collapsible_depends_on": null,
  "columns": 0,
  "default": null,
  "depends_on": null,
  "description": null,
  "docstatus": 0,
  "doctype": "Custom Field",
  "dt": "Payment Entry Detail",
  "fetch_from": null,
  "fetch_if_empty": 0,
  "fieldname": "payment",
  "fieldtype": "Check",
  "hidden": 0,
  "hide_border": 0,
  "hide_days": 0,
  "hide_seconds": 0,
  "ignore_user_permissions": 0,
  "ignore_xss_filter": 0,
  "in_global_search": 0,
  "in_list_view": 1,
  "in_preview": 0,
  "in_standard_filter": 0,
  "insert_after": "payment_entry_details",
  "is_system_generated": 0,
  "is_virtual": 0,
  "label": "Payment",
  "length": 0,
  "mandatory_depends_on": null,
  "modified": "2023-04-05 11:27:12.368753",
  "module": null,
  "name": "Payment Entry Detail-payment",
  "no_copy": 0,
  "non_negative": 0,
  "options": null,
  "permlevel": 0,
  "precision": "",
  "print_hide": 0,
  "print_hide_if_no_value": 0,
  "print_width": null,
  "read_only": 0,
  "read_only_depends_on": null,
  "report_hide": 0,
  "reqd": 0,
  "search_index": 0,
  "translatable": 0,
  "unique": 0,
  "width": null
 },
 {
  "allow_in_quick_entry": 0,
  "allow_on_submit": 0,
  "bold": 0,
  "collapsible": 0,
  "collapsible_depends_on": null,
  "columns": 0,
  "default": null,
  "depends_on": null,
  "description": null,
  "docstatus": 0,
  "doctype": "Custom Field",
  "dt": "Payment Entry Detail",
  "fetch_from": null,
  "fetch_if_empty": 0,
  "fieldname": "view",
  "fieldtype": "Button",
  "hidden": 0,
  "hide_border": 0,
  "hide_days": 0,
  "hide_seconds": 0,
  "ignore_user_permissions": 0,
  "ignore_xss_filter": 0,
  "in_global_search": 0,
  "in_list_view": 1,
  "in_preview": 0,
  "in_standard_filter": 0,
  "insert_after": "payment",
  "is_system_generated": 0,
  "is_virtual": 0,
  "label": "Allocation",
  "length": 0,
  "mandatory_depends_on": null,
  "modified": "2023-04-01 08:06:40.634215",
  "module": null,
  "name": "Payment Entry Detail-view",
  "no_copy": 0,
  "non_negative": 0,
  "options": null,
  "permlevel": 0,
  "precision": "",
  "print_hide": 0,
  "print_hide_if_no_value": 0,
  "print_width": null,
  "read_only": 0,
  "read_only_depends_on": "",
  "report_hide": 0,
  "reqd": 0,
  "search_index": 0,
  "translatable": 0,
  "unique": 0,
  "width": null
 },
 {
  "allow_in_quick_entry": 0,
  "allow_on_submit": 1,
  "bold": 0,
  "collapsible": 0,
  "collapsible_depends_on": null,
  "columns": 0,
  "default": null,
  "depends_on": null,
  "description": null,
  "docstatus": 0,
  "doctype": "Custom Field",
  "dt": "Purchase Invoice",
  "fetch_from": null,
  "fetch_if_empty": 0,
  "fieldname": "paid_amount",
  "fieldtype": "Float",
  "hidden": 0,
  "hide_border": 0,
  "hide_days": 0,
  "hide_seconds": 0,
  "ignore_user_permissions": 0,
  "ignore_xss_filter": 0,
  "in_global_search": 0,
  "in_list_view": 0,
  "in_preview": 0,
  "in_standard_filter": 0,
  "insert_after": "rounded_total",
  "is_system_generated": 0,
  "is_virtual": 0,
  "label": "Paid Amount",
  "length": 0,
  "mandatory_depends_on": null,
  "modified": "2023-03-30 12:12:36.489760",
  "module": null,
  "name": "Purchase Invoice-paid_amount",
  "no_copy": 0,
  "non_negative": 0,
  "options": null,
  "permlevel": 0,
  "precision": "",
  "print_hide": 0,
  "print_hide_if_no_value": 0,
  "print_width": null,
  "read_only": 0,
  "read_only_depends_on": null,
  "report_hide": 0,
  "reqd": 0,
  "search_index": 0,
  "translatable": 0,
  "unique": 0,
  "width": null
 },
 {
  "allow_in_quick_entry": 0,
  "allow_on_submit": 1,
  "bold": 0,
  "collapsible": 0,
  "collapsible_depends_on": null,
  "columns": 0,
  "default": null,
  "depends_on": null,
  "description": null,
  "docstatus": 0,
  "doctype": "Custom Field",
  "dt": "Purchase Invoice",
  "fetch_from": null,
  "fetch_if_empty": 0,
  "fieldname": "balance_ammount",
  "fieldtype": "Float",
  "hidden": 0,
  "hide_border": 0,
  "hide_days": 0,
  "hide_seconds": 0,
  "ignore_user_permissions": 0,
  "ignore_xss_filter": 0,
  "in_global_search": 0,
  "in_list_view": 0,
  "in_preview": 0,
  "in_standard_filter": 0,
  "insert_after": "paid_amount",
  "is_system_generated": 0,
  "is_virtual": 0,
  "label": "Balance Ammount",
  "length": 0,
  "mandatory_depends_on": null,
  "modified": "2023-03-30 12:12:36.791294",
  "module": null,
  "name": "Purchase Invoice-balance_ammount",
  "no_copy": 0,
  "non_negative": 0,
  "options": null,
  "permlevel": 0,
  "precision": "",
  "print_hide": 0,
  "print_hide_if_no_value": 0,
  "print_width": null,
  "read_only": 0,
  "read_only_depends_on": null,
  "report_hide": 0,
  "reqd": 0,
  "search_index": 0,
  "translatable": 0,
  "unique": 0,
  "width": null
 }
]